baiduTrans/__init__.py
baiduTrans/__version__.py
baiduTrans/baidu_Translator_zh_en.py
baidu_Translator_zh_en-0.0.1.dist-info/LICENSE
baidu_Translator_zh_en-0.0.1.dist-info/METADATA
baidu_Translator_zh_en-0.0.1.dist-info/WHEEL
baidu_Translator_zh_en-0.0.1.dist-info/top_level.txt
baidu_Translator_zh_en-0.0.1.dist-info/RECORD
