Metadata-Version: 2.1
Name: baidu-Translator-zh-en
Version: 0.0.1
Summary: a library for oprate the baidu translator
Home-page: https://github.com/YinglongCao/baiduAPI
Author: Yinglong Cao
Author-email: 18817005523@163.com
License: GPL License
Keywords: baidu translate
Platform: any
